{
    "format_version": "1.8.0",
    "render_controllers": {
      "controller.render.helmet.chainmail.turn_red": {
        "geometry": "Geometry.helmet",
        "materials": [ { "*": "Material.default" } ],
        "textures": [ "Texture.chainmail_1" ],
        "is_hurt_color": {
          "r": "1.0",
          "g": "0.0",
          "b": "0.0",
          "a": "0.6"
        }
      },
      "controller.render.chestplate.chainmail.turn_red": {
        "geometry": "Geometry.chestplate",
        "materials": [ { "*": "Material.default" } ],
        "textures": [ "Texture.chainmail_1" ],
        "is_hurt_color": {
          "r": "1.0",
          "g": "0.0",
          "b": "0.0",
          "a": "0.6"
        }
      },
      "controller.render.leggings.chainmail.turn_red": {
        "geometry": "Geometry.leggings",
        "materials": [ { "*": "Material.default" } ],
        "textures": [ "Texture.chainmail_2" ],
        "is_hurt_color": {
          "r": "1.0",
          "g": "0.0",
          "b": "0.0",
          "a": "0.6"
        }
      },
      "controller.render.boots.chainmail.turn_red": {
        "geometry": "Geometry.boots",
        "materials": [ { "*": "Material.default" } ],
        "textures": [ "Texture.chainmail_1" ],
        "is_hurt_color": {
          "r": "1.0",
          "g": "0.0",
          "b": "0.0",
          "a": "0.6"
        }
      }
    }
  }