{"minecraft:tree_feature":{"may_grow_through":["minecraft:dirt","minecraft:grass","minecraft:moss_carpet","minecraft:tallgrass","minecraft:sunflower","minecraft:lilac","minecraft:tall_grass","minecraft:large_fern","minecraft:rose_bush","minecraft:peony"],"base_block":["minecraft:dirt_with_roots"],"description":{"identifier":"minecraft:azalea_tree_feature"},"may_grow_on":["minecraft:dirt","minecraft:grass","minecraft:podzol","minecraft:dirt","minecraft:farmland","minecraft:dirt_with_roots","minecraft:moss_block","minecraft:clay","minecraft:mycelium","minecraft:mud","minecraft:muddy_mangrove_roots"],"acacia_trunk":{"trunk_block":{"states":{"old_log_type":"oak"},"name":"minecraft:log"},"trunk_height":{"intervals":[2],"base":4,"min_height_for_canopy":3},"trunk_width":1,"trunk_lean":{"lean_steps":{"range_max":4,"range_min":3},"lean_height":{"range_max":3,"range_min":2},"lean_length":{"range_max":2,"range_min":1},"allow_diagonal_growth":true}},"random_spread_canopy":{"leaf_placement_attempts":50,"canopy_height":2,"leaf_blocks":[["minecraft:azalea_leaves",3],["minecraft:azalea_leaves_flowered",1]],"canopy_radius":3},"may_replace":["minecraft:leaves","minecraft:leaves2","minecraft:azalea","minecraft:flowering_azalea","minecraft:azalea_leaves","minecraft:azalea_leaves_flowered","minecraft:mangrove_leaves","minecraft:water","minecraft:flowing_water","minecraft:moss_carpet","minecraft:tallgrass","minecraft:grass","minecraft:air","minecraft:sunflower","minecraft:lilac","minecraft:tall_grass","minecraft:large_fern","minecraft:rose_bush","minecraft:peony"]},"format_version":"1.13.0"}