{"button_label":{"shadow":false,"font_type":"smooth","max_size":["100%","100%"],"layer":"$label_layer","font_scale_factor":"$label_font_scale_factor","text_alignment":"center","type":"label","alpha":"$control_alpha","font_size":"$label_font_size","offset":"$label_offset","text":"$label_text","color":"$label_color"},"main":{"is_showing_menu":true,"force_render_below":false,"should_steal_mouse":false,"always_accepts_input":false,"type":"screen","controls":[{"main_pnl@new_netease_shop_desk.main_pnl":{}}],"render_game_behind":true,"absorbs_input":true,"render_only_when_topmost":true},"main_pnl":{"priority":0,"visible":true,"clips_children":false,"anchor_from":"center","propagate_alpha":false,"anchor_to":"center","max_size":[0,0],"layer":1,"enabled":true,"controls":[{"btn_shop@new_netease_shop_desk.btn_shop":{}}],"type":"panel","alpha":1.0,"size":["100.0%+0.0px","100.0%+0.0px"],"offset":[0,0],"clip_offset":[0,0],"min_size":[0,0]},"default":{"nine_slice_buttom":"$nine_slice_buttom","nine_slice_left":"$nine_slice_left","texture":"$default_texture","layer":"$texture_layer","type":"image","alpha":"$control_alpha","nineslice_size":"$nineslice_size","nine_slice_right":"$nine_slice_right","nine_slice_top":"$nine_slice_top","is_new_nine_slice":"$is_new_nine_slice"},"btn_shop@common.button":{"$nine_slice_top":1,"$hover_texture":"textures/ui/netease_shop/btn01_hover","$pressed_texture":"textures/ui/netease_shop/btn01_click","$nine_slice_right":1,"button_mappings":[],"$nine_slice_left":1,"visible":true,"$pressed_button_name":"%new_netease_shop_desk.click","anchor_to":"top_left","is_handle_button_move_event":true,"$control_alpha":0.66000002622604,"$is_new_nine_slice":true,"$label_offset":[0,0],"clip_offset":[0,0],"$label_text":"","anchor_from":"top_left","$label_color":[0.0,0.0,0.0],"draggable":"not_draggable","enabled":true,"$label_layer":3,"offset":[20.0,20.0],"$label_font_size":"normal","$label_font_scale_factor":0.93999999761581,"propagate_alpha":false,"$texture_layer":2,"$nineslice_size":[0,0,0,0],"controls":[{"default@new_netease_shop_desk.default":{}},{"hover@new_netease_shop_desk.hover":{}},{"pressed@new_netease_shop_desk.pressed":{}},{"button_label@new_netease_shop_desk.button_label":{}}],"max_size":[0,0],"$default_texture":"textures/ui/netease_shop/gui3","$nine_slice_buttom":1,"clips_children":false,"alpha":1.0,"size":[20,20],"bindings":[{"binding_type":"collection_details","binding_collection_name":"","binding_condition":"always_when_visible"}],"priority":0,"min_size":[0,0]},"hover":{"nine_slice_buttom":"$nine_slice_buttom","nine_slice_left":"$nine_slice_left","texture":"$hover_texture","layer":"$texture_layer","type":"image","alpha":"$control_alpha","nineslice_size":"$nineslice_size","nine_slice_right":"$nine_slice_right","nine_slice_top":"$nine_slice_top","is_new_nine_slice":"$is_new_nine_slice"},"pressed":{"nine_slice_buttom":"$nine_slice_buttom","nine_slice_left":"$nine_slice_left","texture":"$pressed_texture","layer":"$texture_layer","type":"image","alpha":"$control_alpha","nineslice_size":"$nineslice_size","nine_slice_right":"$nine_slice_right","nine_slice_top":"$nine_slice_top","is_new_nine_slice":"$is_new_nine_slice"},"namespace":"new_netease_shop_desk"}