{"header":{"type":"panel","anchor_from":"top_middle","size":["100%",28],"anchor_to":"top_middle","controls":[{"closeBtn@petBagUI.closeBtn":{}},{"headerName1@petBagUI.headerName":{"$header_name":"物品栏","offset":["-25%",0]}},{"headerName2@petBagUI.headerName":{"$header_name":"伙伴背包","offset":["25%",0]}},{"headerBg@petBagUI.headerBg":{}}]},"bagContent":{"type":"panel","anchor_from":"center","size":["80%","84%"],"anchor_to":"center","offset":[0,-16],"controls":[{"scrollingPanel@petBagUI.scrollingPanel":{}},{"dropArea@petBagUI.dropButton":{}}]},"headerContentStackPanel":{"type":"stack_panel","controls":[{"header@petBagUI.header":{}},{"contentPanel@petBagUI.contentPanel":{}}],"orientation":"vertical","size":["100%","100%"],"layer":2},"namespace":"petBagUI","itemNum":{"visible":true,"anchor_from":"bottom_right","text":"","layer":4,"font_type":"smooth","text_alignment":"right","type":"label","shadow":true,"size":["55%","40%"],"offset":[2,3],"font_size":"normal","anchor_to":"bottom_right"},"unlockHint":{"visible":false,"anchor_from":"center","anchor_to":"center","layer":50,"type":"image","size":["100%c","100%c + 8px"],"nineslice_size":4,"texture":"textures/ui/hint_tip_bg","controls":[{"hintPanel":{"controls":[{"hintTitle":{"anchor_from":"top_middle","text":"解锁条件","layer":1,"text_alignment":"center","type":"label","anchor_to":"top_middle","size":["default",16],"offset":[0,2],"shadow":true,"color":[0.762,0.762,0.762]}},{"hintText":{"anchor_to":"top_middle","text_alignment":"center","type":"label","anchor_from":"top_middle","size":["default",14],"text":"","offset":[0,16],"layer":1}}],"size":["100%c",28],"type":"panel","layer":30}}]},"petBagPanel":{"visible":true,"type":"panel","anchor_from":"top_middle","controls":[{"headerContentStackPanel@petBagUI.headerContentStackPanel":{}},{"background@petBagUI.background":{}},{"itemDetail@petBagUI.itemDetail":{}},{"unlockHint@petBagUI.unlockHint":{}},{"dropArea@petBagUI.dropButton":{"layer":3}},{"progressiveBar@petBagUI.progressBar":{"$progressBarSize":[18,3],"$barMaskSize":["100.0%+0.0px","100.0%+0.0px"]}}],"anchor_to":"top_middle","offset":[0,0],"layer":1},"itemLockYellow":{"texture":"textures/ui/item_lock_yellow","visible":false,"type":"image","layer":4},"headerName":{"visible":true,"anchor_from":"center","$header_name|default":"","anchor_to":"center","text":"$header_name","layer":23,"font_type":"smooth","text_alignment":"center","type":"label","offset":[0,0],"size":[60,"50%"],"shadow":false,"font_size":"normal","color":[0,0,0]},"headerBg":{"visible":true,"type":"image","texture":"textures/ui/header_bar","nineslice_size":[3,3,3,6],"layer":3},"closeBtn@common.button":{"$label_text":"x","$hover_texture":"","anchor_from":"top_right","$label_color":[0,0,0],"$pressed_texture":"","$label_layer":3,"$default_texture":"","offset":[0,0],"$label_font_size":"normal","visible":true,"$pressed_button_name":"","$texture_layer":2,"anchor_to":"top_right","layer":22,"$label_offset":[0,0],"controls":[{"default@petBagUI.default":{}},{"hover@petBagUI.hover":{}},{"pressed@petBagUI.pressed":{}},{"button_label@petBagUI.button_label":{}}],"size":[28,"100%"],"type":"button"},"main@common.base_screen":{"$screen_content":"petBagUI.petBagPanel"},"hover":{"texture":"$hover_texture","nineslice_size":1,"type":"image","layer":"$texture_layer"},"itemBtn@common.button":{"$hover_texture":"textures/ui/cell_image","anchor_from":"$item_button_anchor_from","$item_button_anchor_from|default":"center","$pressed_texture":"textures/ui/cell_image","$item_button_offset|default":[0,0],"$item_button_layer|default":1,"type":"button","button_mappings":[],"pressed_control":"pressed","visible":true,"$pressed_button_name":"","$texture_layer":2,"anchor_to":"$item_button_anchor_to","is_handle_button_move_event":true,"layer":"$item_button_layer","$item_button_size|default":[28,28],"$item_button_anchor_to|default":"center","default_control":"default","hover_control":"hover","size":"$item_button_size","controls":[{"selectedImg@petBagUI.selectedImg":{}},{"default@petBagUI.default":{}},{"hover@petBagUI.hover":{}},{"pressed@petBagUI.pressed":{}},{"itemImg@petBagUI.itemImg":{}},{"durabilityBar@petBagUI.progressBar":{}},{"itemLockYellow@petBagUI.itemLockYellow":{}},{"itemLockRed@petBagUI.itemLockRed":{}},{"lockedImg":{"color":[0,0,0],"visible":false,"type":"image","alpha":0.3,"size":["100% - 2px","100% - 2px"],"texture":"textures/ui/White","controls":[{"img":{"texture":"textures/ui/pet_ani_lock","type":"image","layer":1}}],"layer":10}}],"offset":"$item_button_offset","$default_texture":"textures/ui/cell_image"},"leftPanel":{"controls":[{"bagContent@petBagUI.bagContent":{}}],"visible":true,"type":"panel","anchor_from":"left_middle","size":["50%","100%"],"anchor_to":"left_middle","offset":[0,0],"layer":0},"button_label":{"font_type":"smooth","layer":"$label_layer","text":"$label_text","text_alignment":"center","type":"label","max_size":["100%","100%"],"font_size":"$label_font_size","shadow":false,"offset":[0,0],"color":"$label_color"},"flyImg":{"anchor_from":"top_left","visible":true,"type":"custom","renderer":"inventory_item_renderer","size":[24,24],"anchor_to":"top_left","offset":[0,0],"layer":33},"progressBar":{"visible":false,"$progressBarSize|default":[18,2],"texture":"textures/ui/white_bg","$progressBarOffset|default":[0,8],"layer":20,"type":"image","controls":[{"barMask":{"visible":true,"anchor_from":"center","$barMaskSize|default":["100.0%+0.0px",1],"texture":"textures/ui/white_bg","layer":21,"anchor_to":"center","type":"image","clip_direction":"left","size":"$barMaskSize","offset":[0,0],"nineslice_size":1,"color":[0,1,0]}}],"size":"$progressBarSize","nineslice_size":1,"offset":"$progressBarOffset","color":[0.3,0.3,0.3]},"contentPanel":{"type":"panel","controls":[{"leftPanel@petBagUI.leftPanel":{}},{"rightPanel@petBagUI.rightPanel":{}},{"flyImgTemplate@petBagUI.flyImg":{}}]},"bagGrid":{"grid_rescaling_type":"horizontal","grid_item_template":"petBagUI.itemBtn","$bag_grid_num|default":36,"anchor_to":"top_left","layer":4,"maximum_grid_items":"$bag_grid_num","collection_name":"bag_grid","size":["100%","default"],"anchor_from":"top_left","type":"grid","visible":true},"petBagContent":{"type":"panel","anchor_from":"center","size":["80%","84%"],"anchor_to":"center","offset":[0,-16],"controls":[{"scrollingPanel@petBagUI.scrollingPanel":{"$bag_grid_num":6}}]},"background":{"visible":true,"anchor_from":"center","anchor_to":"center","layer":2,"type":"image","size":["100.0%+0.0px","100.0%+0.0px"],"nineslice_size":4,"texture":"textures/ui/background_panel","offset":[0,0]},"scrollingPanel@common.scrolling_panel":{"$scroll_size":["8px","100%"],"visible":true,"layer":1,"anchor_from":"center","$scrolling_pane_size":["100%","100%"],"anchor_to":"center","$scrolling_content":"petBagUI.bagGrid","$scroll_box_mouse_image_control":"common-classic.button_state_default"},"itemImg":{"visible":true,"anchor_from":"center","anchor_to":"center","layer":3,"type":"custom","controls":[{"itemNum@petBagUI.itemNum":{}}],"offset":[0,0],"size":[24,24],"renderer":"inventory_item_renderer"},"selectedImg":{"visible":false,"anchor_from":"center","anchor_to":"center","layer":5,"type":"image","size":["100.0%+4.0px","100.0%+4.0px"],"offset":[0,0],"texture":"textures/ui/pocket_ui_highlight_selected_slot","nineslice_size":4},"itemDetail":{"anchor_from":"bottom_middle","offset":"$offset","type":"panel","$offset|default":[0,"-16px"],"controls":[{"itemDetailBg":{"propagate_alpha":true,"texture":"textures/ui/purpleBorder","layer":30,"bindings":[{"binding_name_override":"#alpha","binding_name":"#itemDetailAlpha","binding_condition":"always_when_visible"}],"type":"image","alpha":"#itemDetailAlpha","size":["100%c + 8px","100%c + 8px"],"nineslice_size":4,"controls":[{"itemDetailText":{"text":"","type":"label","layer":1}}]}}],"anchor_to":"bottom_middle","size":["100%c","100%c"],"layer":30},"default":{"texture":"$default_texture","nineslice_size":1,"type":"image","layer":"$texture_layer"},"rightPanel":{"controls":[{"petBagContent@petBagUI.petBagContent":{}}],"visible":true,"type":"panel","anchor_from":"right_middle","size":["50%","100%"],"anchor_to":"right_middle","offset":[0,0],"layer":0},"itemLockRed":{"texture":"textures/ui/item_lock_red","visible":false,"type":"image","layer":4},"pressed":{"texture":"$pressed_texture","nineslice_size":1,"type":"image","layer":"$texture_layer"},"dropButton@common.button":{"$hover_texture":"textures/ui/cell_image","anchor_from":"center","$pressed_texture":"textures/ui/cell_image","type":"button","button_mappings":[],"pressed_control":"pressed","visible":true,"$pressed_button_name":"","$texture_layer":-10,"anchor_to":"center","layer":1,"hover_control":"hover","offset":[0,0],"controls":[{"default@petBagUI.default":{}},{"hover@petBagUI.hover":{}},{"pressed@petBagUI.pressed":{}}],"default_control":"default","size":["100%","100%"],"$default_texture":"textures/ui/cell_image"}}