{"permission_level_dropdown@settings_common.option_dropdown":{"$dropdown_name":"permission_level_dropdown","$dropdown_scroll_content_size":["100%","245%"],"$button_type_panel":"permissions.permission_level_dropdown_state_content","$dropdown_content":"permissions.permission_level_dropdown_content","$default_focus_precedence":2,"$option_enabled_binding_name":"#can_edit_permissions","$option_dropdown_type":"common.dropdown_no_scrollpanel","$option_label":"permissions.level","$dropdown_area":"permissions_options_scrolling_panel","$options_dropdown_toggle_label_binding":"#permission_level_dropdown_label","$focus_override_up":"back_button"},"permissions_options_grid_item":{"controls":[{"option_label_panel":{"size":["fill","100%"],"type":"panel","controls":[{"option_label@permissions.option_label":{"size":["100%","default"],"anchor_to":"left_middle","anchor_from":"left_middle"}}]}},{"option_state_label_panel":{"size":["100%c + 8px","100%"],"type":"panel","controls":[{"option_state_label@permissions.option_state_label":{"size":["default","default"],"anchor_to":"center","anchor_from":"center"}}]}},{"option_toggle@permissions.option_toggle":{"size":[30,"100%"],"$toggle_tts_header_binding_type":"collection","$toggle_tts_header_binding_collection_name":"permissions_collection","$toggle_tts_header":"#option_name"}}],"size":["100%",24],"type":"stack_panel","orientation":"horizontal"},"permissions_member_radio_visuals_normal@settings_common.radio_visuals":{"$radio_texture":"textures/ui/permissions_member_star"},"namespace":"permissions","back_button@common_buttons.no_background_content_button":{"$button_content":"permissions.back_button_content","$button_binding_condition|default":"none","$button_type_panel":"common_buttons.form_fitting_button_content_panel","layer":2,"$focus_id":"back_button","$button_text|default":"gui.back","button_mappings":[{"from_button_id":"button.menu_select","to_button_id":"button.menu_exit","mapping_type":"pressed"},{"from_button_id":"button.menu_ok","to_button_id":"button.menu_exit","mapping_type":"focused"}],"$button_text_grid_collection_name|default":"","$button_text_binding_type|default":"none"},"gamertag_label":{"bindings":[{"binding_type":"collection","binding_name":"#gamertag","binding_collection_name":"players_collection"}],"type":"label","anchor_from":"left_middle","color":"$main_header_text_color","text":"#gamertag","anchor_to":"left_middle","layer":2},"radio_content_with_title_bar":{"orientation":"vertical","offset":[4,0],"type":"stack_panel","controls":[{"title_and_icon@permissions.radio_title_and_icon":{}},{"helper_text":{"shadow":false,"type":"label","font_type":"smooth","size":["100%-8px","default"],"font_scale_factor":1.333,"text":"$radio_label_desc","color":"$main_header_text_color"}},{"bottom_padding":{"type":"panel","size":["100%",2]}}]},"permissions_member_visuals_with_title_normal@permissions.radio_visuals_with_title":{"$radio_texture":"textures/ui/permissions_member_star"},"ban_button@common_buttons.light_text_button":{"bindings":[{"binding_name_override":"#visible","binding_name":"#ban_button_visible","binding_type":"global"},{"binding_name":"#ban_button_enabled","binding_name_override":"#enabled"}],"focus_change_down":"FOCUS_OVERRIDE_STOP","$pressed_button_name":"button.ban","$button_text":"permissionsScreen.ban","$focus_override_right":"FOCUS_OVERRIDE_STOP","size":["100%",28],"layer":2},"selector_area@common.modal_area_panel_base":{"$menu_cancel_button_id":"button.menu_exit","controls":[{"player_scrolling_panel@common.scrolling_panel":{"$show_background":false,"$scrolling_content":"permissions.players_grid_panel"}}],"$modal_binding_name":"#selector_area_focused","size":["154px","95%"],"layer":2},"option_state_label":{"bindings":[{"binding_type":"collection","binding_name":"#option_state_name","binding_collection_name":"permissions_collection"}],"type":"label","text":"#option_state_name","color":"$main_header_text_color","layer":2},"permissions_visitor_visuals_with_title_normal@permissions.radio_visuals_with_title":{"$radio_texture":"textures/ui/permissions_visitor_hand"},"ip_label":{"bindings":[{"binding_name_override":"#ip","binding_name":"#ip_address_text","binding_condition":"visibility_changed"}],"type":"label","ignored":"(not $education_edition)","size":["default","default"],"text":"#ip","color":"$main_header_text_color","layer":1},"permissions_options_stack_panel":{"orientation":"vertical","type":"stack_panel","controls":[{"permissions_padding_0":{"size":["100%",8],"bindings":[{"binding_name":"#is_world_template_locked","binding_name_override":"#visible"}],"type":"panel"}},{"world_template_option_lock_panel":{"size":["100%","100%c"],"bindings":[{"binding_name":"#is_world_template_locked","binding_name_override":"#visible"}],"type":"panel","controls":[{"option_info_label@settings_common.option_info_label":{"$container_text_binding_name":"#world_template_permissions_locked_warning_text","$show_option_label":false}}]}},{"permissions_padding_1":{"type":"panel","size":["100%",8]}},{"permission_level_dropdown@permissions.permission_level_dropdown":{}},{"permissions_padding_2":{"type":"panel","size":["100%",2]}},{"permissions_options_grid@permissions.permissions_options_grid":{}},{"permissions_padding_3":{"type":"panel","size":["100%",4]}},{"permissions_kick_button_panel@permissions.permissions_kick_button_panel":{}},{"permissions_padding_4":{"type":"panel","size":["100%",4]}},{"permissions_ban_button_panel@permissions.permissions_ban_button_panel":{}},{"permissions_padding_5":{"type":"panel","size":["100%",4]}}]},"kick_button@common_buttons.light_text_button":{"bindings":[{"binding_name_override":"#visible","binding_name":"#kick_button_visible","binding_type":"global"},{"binding_name":"#kick_button_enabled","binding_name_override":"#enabled"}],"focus_change_down":"button.ban","$pressed_button_name":"button.kick","$button_text":"permissionsScreen.kick","$focus_override_right":"FOCUS_OVERRIDE_STOP","size":["100%",28],"layer":2},"option_label":{"bindings":[{"binding_type":"collection","binding_name":"#option_name","binding_collection_name":"permissions_collection"}],"type":"label","size":["100%","default"],"text":"#option_name","color":"$main_header_text_color","layer":2},"permissions_op_radio_visuals_hover@settings_common.radio_visuals":{"$radio_texture":"textures/ui/permissions_op_crown_hover"},"permissions_op_visuals_with_title_normal@permissions.radio_visuals_with_title":{"$radio_texture":"textures/ui/permissions_op_crown"},"back_button_content":{"controls":[{"chevron_panel":{"size":["100%c","100%c"],"type":"panel","controls":[{"left_chevron@common.chevron_image":{"texture":"textures/ui/chevron_left","offset":[0,1],"color":"$text_color"}}]}},{"back_button_padding":{"type":"panel","size":[4,"100%"]}},{"label_panel":{"size":["100%c","100%c"],"type":"panel","controls":[{"label@common_buttons.new_ui_binding_button_label":{"offset":[0,0]}}]}}],"size":["100%c",16],"type":"stack_panel","orientation":"horizontal"},"player_local_icon":{"bindings":[{"binding_collection_name":"players_collection","binding_name_override":"#visible","binding_name":"#local_icon_visible","binding_type":"collection"}],"type":"image","size":[13,13],"texture":"textures/ui/lan_icon","layer":1},"player_pic_panel":{"type":"panel","anchor_from":"left_middle","size":[20,"100%"],"anchor_to":"left_middle","offset":[1,0],"controls":[{"player_gamer_pic@permissions.player_gamer_pic":{}},{"player_local_icon@permissions.player_local_icon":{}}]},"top_bar_panel":{"size":["100%",23],"type":"panel","controls":[{"top_bar@permissions.top_bar":{}},{"back_button@permissions.back_button":{"anchor_to":"left_middle","bindings":[{"binding_name":"(not #is_using_gamepad)","binding_name_override":"#visible"}],"anchor_from":"left_middle"}},{"gamepad_helper_b@common.gamepad_helper_b":{"$icon_description_bind":"#b_button_text","offset":[1,-6],"anchor_from":"left_middle","size":["100%c",16],"anchor_to":"left_middle","$gamepad_helper_visible_binding_name":"#is_using_gamepad","$icon_description_bind_type":"global"}},{"title_label@permissions.title_label":{}}]},"permissions_custom_radio_visuals_normal@settings_common.radio_visuals":{"$radio_texture":"textures/ui/permissions_custom_dots"},"permissions_options_grid":{"grid_dimension_binding":"#permissions_grid_dimension","bindings":[{"binding_name":"#permissions_grid_dimension"},{"binding_name":"#permission_options_grid_visible","binding_name_override":"#visible"}],"type":"grid","grid_item_template":"permissions.permissions_options_grid_item","size":["100%","default"],"collection_name":"permissions_collection"},"content_panel":{"size":["default","fill"],"type":"panel","controls":[{"content_stack_panel":{"controls":[{"content_padding_1":{"type":"panel","size":["100%",4]}},{"ip_label@permissions.ip_label":{}},{"world_label@permissions.world_label":{}},{"content_padding_2":{"type":"panel","size":["100%",4]}},{"player_and_permissions_panel@permissions.player_and_permissions_panel":{}}],"size":["88%","100%"],"type":"stack_panel","orientation":"vertical"}}]},"permission_level_dropdown_content@settings_common.option_radio_dropdown_group":{"$is_world_settings|default":false,"$radio_buttons":[{"permission_level_radio_visitor@permissions.permission_level_radio":{"$toggle_state_binding_name":"#permission_level_radio_visitor","$permissions_visuals_normal":"permissions.permissions_visitor_radio_visuals_normal","$permissions_visuals_hover":"permissions.permissions_visitor_radio_visuals_hover","$radio_label_text":"permissions.level.visitor","ignored":"$is_world_settings"}},{"permission_level_radio_visitor_settings@permissions.permission_level_radio":{"$toggle_state_binding_name":"#permission_level_radio_visitor","$permissions_visuals_normal":"permissions.permissions_visitor_visuals_with_title_normal","$permissions_visuals_hover":"permissions.permissions_visitor_visuals_with_title_hover","ignored":"(not $is_world_settings)","$radio_label_text":"permissions.level.visitor","$radio_label_desc":"permissions.description.visitors"}},{"permission_level_radio_member@permissions.permission_level_radio":{"$toggle_state_binding_name":"#permission_level_radio_member","$permissions_visuals_normal":"permissions.permissions_member_radio_visuals_normal","$permissions_visuals_hover":"permissions.permissions_member_radio_visuals_hover","$radio_label_text":"permissions.level.member","ignored":"$is_world_settings"}},{"permission_level_radio_member_settings@permissions.permission_level_radio":{"$toggle_state_binding_name":"#permission_level_radio_member","$permissions_visuals_normal":"permissions.permissions_member_visuals_with_title_normal","$permissions_visuals_hover":"permissions.permissions_member_visuals_with_title_hover","ignored":"(not $is_world_settings)","$radio_label_text":"permissions.level.member","$radio_label_desc":"permissions.description.members"}},{"permission_level_radio_operator@permissions.permission_level_radio":{"$toggle_state_binding_name":"#permission_level_radio_operator","$permissions_visuals_normal":"permissions.permissions_op_radio_visuals_normal","$permissions_visuals_hover":"permissions.permissions_op_radio_visuals_hover","$radio_label_text":"permissions.level.operator","ignored":"$is_world_settings"}},{"permission_level_radio_operator_settings@permissions.permission_level_radio":{"$toggle_state_binding_name":"#permission_level_radio_operator","$permissions_visuals_normal":"permissions.permissions_op_visuals_with_title_normal","$permissions_visuals_hover":"permissions.permissions_op_visuals_with_title_hover","ignored":"(not $is_world_settings)","$radio_label_text":"permissions.level.operator","$radio_label_desc":"permissions.description.operators"}},{"permission_level_radio_custom@permissions.permission_level_radio":{"$toggle_state_binding_name":"#permission_level_radio_custom","$permissions_visuals_normal":"permissions.permissions_custom_radio_visuals_normal","$permissions_visuals_hover":"permissions.permissions_custom_radio_visuals_hover","$radio_label_text":"permissions.level.custom","ignored":"($is_world_settings or $is_in_realm)"}}],"$is_in_realm|default":false},"player_gamer_pic":{"texture_file_system":"#texture_source","bindings":[{"binding_type":"collection","binding_name":"#texture","binding_collection_name":"players_collection"},{"binding_type":"collection","binding_name_override":"#texture_file_system","binding_collection_name":"players_collection","binding_name":"#texture_source"},{"binding_collection_name":"players_collection","binding_name_override":"#visible","binding_name":"#gamerpic_visible","binding_type":"collection"}],"type":"image","size":[18,18],"texture":"#texture","controls":[{"player_panel_black_border@common.square_image_border_white":{"size":["100% + 2px","100% + 2px"],"anchor_to":"center","color":[0,0,0],"anchor_from":"center"}}],"layer":1},"permissions_kick_button_panel":{"size":["100%","100%c"],"type":"panel","controls":[{"kick_button@permissions.kick_button":{}}]},"radio_visuals_with_title":{"size":["100%-4px","100%c"],"offset":[-2,0],"type":"panel","controls":[{"radio_content@permissions.radio_content_with_title_bar":{}}]},"permissions_member_radio_visuals_hover@settings_common.radio_visuals":{"$radio_texture":"textures/ui/permissions_member_star_hover"},"permissions_screen_content":{"type":"stack_panel","anchor_from":"top_middle","orientation":"vertical","anchor_to":"top_middle","size":["100%","100%"],"controls":[{"top_bar_panel@permissions.top_bar_panel":{}},{"content_panel@permissions.content_panel":{}}]},"permissions_ban_button_panel":{"size":["100%","100%c"],"type":"panel","controls":[{"ban_button@permissions.ban_button":{}}]},"banner_background":{"type":"image","texture":"textures/ui/Banners"},"players_grid_panel":{"size":["100%","100%c"],"type":"panel","controls":[{"players_grid@permissions.players_grid":{}}]},"player_grid_item":{"size":["100%",27],"type":"panel","controls":[{"player_toggle@permissions.player_toggle":{"size":["100%","100% + 1px"],"anchor_to":"top_middle","anchor_from":"top_middle"}},{"inactive_modal_pane_fade@common.inactive_modal_pane_fade":{"texture":"textures/ui/permissions_player_fade_overlay","bindings":[{"binding_name":"#content_area_focused","binding_name_override":"#visible"}]}}]},"radio_visuals_with_title_hover":{"type":"image","controls":[{"radio_content@permissions.radio_content_with_title_bar":{}}],"offset":[-2,0],"texture":"textures/ui/focus_border_white","size":["100%-4px","100%c"]},"top_bar":{"texture":"textures/ui/StoreTopBar","type":"image","layer":1},"player_and_permissions_panel":{"controls":[{"selector_area@permissions.selector_area":{}},{"content_area@permissions.content_area":{}}],"size":["100%","fill"],"type":"stack_panel","orientation":"horizontal"},"permissions_visitor_radio_visuals_hover@settings_common.radio_visuals":{"$radio_texture":"textures/ui/permissions_visitor_hand_hover"},"permission_level_radio@settings_common.radio_with_label":{"size":["100%","100%c"],"controls":[{"radio_with_label_core@settings_common.radio_with_label_core":{"$checked_hover_control":"$permissions_visuals_hover","$checked_control":"$permissions_visuals_normal","$unchecked_control":"$permissions_visuals_normal","$unchecked_hover_control":"$permissions_visuals_hover"}}]},"player_button_content":{"controls":[{"player_pic_panel@permissions.player_pic_panel":{}},{"player_button_padding_1":{"type":"panel","size":[4,0]}},{"gamertag_panel":{"size":["fill","100%"],"type":"panel","controls":[{"gamertag_label@permissions.gamertag_label":{"offset":[0,1]}}]}},{"icon_panel":{"controls":[{"dropdown_icon_image":{"size":[15,15],"texture":"#player_permission_level_icon_texture","type":"image","bindings":[{"binding_type":"collection","binding_name_override":"#texture","binding_collection_name":"players_collection","binding_name":"#player_permission_level_icon_texture"}]}}],"size":["100%c","100%"],"type":"panel","layer":1}},{"player_button_padding_2":{"type":"panel","size":[4,0]}}],"type":"stack_panel","anchor_from":"left_middle","orientation":"horizontal","anchor_to":"left_middle","size":["100% - 4px","100% - 4px"],"layer":3},"permissions_op_radio_visuals_normal@settings_common.radio_visuals":{"$radio_texture":"textures/ui/permissions_op_crown"},"option_toggle@common_toggles.switch_toggle_collection":{"$toggle_enabled_binding_name":"#can_edit_permissions","$toggle_grid_collection_name":"permissions_collection","$toggle_binding_type":"collection","$toggle_enabled_binding_type":"global","$toggle_name":"option_toggle","$toggle_state_binding_name":"#option_toggle_state"},"player_toggle@common_toggles.dark_image_toggle_collection":{"$toggle_grid_collection_name":"players_collection","$button_content":"permissions.player_button_content","$toggle_name":"player_toggle","$toggle_state_binding_name":"#player_toggle_state","$radio_toggle_group":true,"$toggle_binding_type":"collection"},"permission_level_dropdown_state_content":{"$content_label_visible|default":true,"controls":[{"icon_panel":{"controls":[{"dropdown_icon_image":{"$dropdown_icon_image_texture_binding|default":"#permission_level_dropdown_icon_texture","$icon_binding_type_override|default":"global","texture":"$dropdown_icon_image_texture_binding","bindings":[{"binding_type":"$icon_binding_type_override","binding_name_override":"#texture","binding_collection_name":"$icon_binding_collection_name_override","binding_name":"$dropdown_icon_image_texture_binding"}],"type":"image","size":"$dropdown_icon_image_size","offset":[0,-1],"$dropdown_icon_image_size|default":[15,15],"$icon_binding_collection_name_override|default":""}}],"size":["100%c","100%"],"type":"panel","layer":1}},{"dropdown_label_padding":{"type":"panel","size":"$padding_size"}},{"label_panel":{"controls":[{"label@common.new_button_label":{"visible":"$content_label_visible","anchor_from":"left_middle","anchor_to":"left_middle","layer":1,"$options_dropdown_label_color_binding|default":"","bindings":[{"binding_name":"$options_dropdown_toggle_label_binding","binding_condition":"none"},{"binding_type":"$options_dropdown_label_color_binding_type","binding_name":"$options_dropdown_label_color_binding","binding_name_override":"#color"}],"$options_dropdown_label_color_binding_type|default":"none","size":["100%","default"],"max_size":["100%","100%"],"text":"$options_dropdown_toggle_label_binding","alpha":"$content_alpha"}}],"size":["fill","100%"],"type":"panel","layer":1}},{"arrow_panel":{"controls":[{"arrow_image@settings_common.arrow_image":{}}],"size":["100%c","100%"],"type":"panel","layer":1}}],"type":"stack_panel","orientation":"horizontal","size":"$content_size","$content_size|default":["100% - 16px","100% - 8px"],"$padding_size|default":[10,0],"layer":3},"permissions_member_visuals_with_title_hover@permissions.radio_visuals_with_title_hover":{"$radio_texture":"textures/ui/permissions_member_star_hover"},"players_grid":{"grid_dimension_binding":"#players_grid_dimension","bindings":[{"binding_name":"#players_grid_dimension"}],"type":"grid","grid_item_template":"permissions.player_grid_item","size":["100%","default"],"anchor_to":"top_left","collection_name":"players_collection","anchor_from":"top_left"},"permissions_screen@common.base_screen":{"button_mappings":[{"from_button_id":"button.menu_cancel","to_button_id":"button.menu_exit","mapping_type":"global"},{"from_button_id":"button.menu_exit","to_button_id":"button.menu_exit","mapping_type":"global"}],"$screen_bg_content":"common.screen_background","$screen_content":"permissions.permissions_screen_content"},"permissions_visitor_visuals_with_title_hover@permissions.radio_visuals_with_title_hover":{"$radio_texture":"textures/ui/permissions_visitor_hand_hover"},"permissions_visitor_radio_visuals_normal@settings_common.radio_visuals":{"$radio_texture":"textures/ui/permissions_visitor_hand"},"world_label":{"type":"label","size":["default","default"],"text":"pauseScreen.currentWorld","color":"$main_header_text_color","layer":1},"permissions_op_visuals_with_title_hover@permissions.radio_visuals_with_title_hover":{"$radio_texture":"textures/ui/permissions_op_crown_hover"},"content_area@common.modal_area_panel_base":{"$menu_cancel_button_id":"button.back_to_selector_area","controls":[{"permissions_options_background":{"type":"panel","controls":[{"permissions_options_background_image@permissions.banner_background":{"size":["100% + 2px","100%"],"controls":[{"permissions_options_scrolling_panel@permissions.permissions_options_scrolling_panel":{}}]}}]}},{"inactive_modal_pane_fade@common.inactive_modal_pane_fade":{"bindings":[{"binding_name":"#selector_area_focused","binding_name_override":"#visible"}]}}],"$modal_binding_name":"#content_area_focused","size":["fill","95%"],"layer":1},"permissions_options_scrolling_panel@common.scrolling_panel":{"size":["100% - 2px","100% - 2px"],"$show_background":false,"$scrolling_content":"permissions.permissions_options_panel","$always_handle_scrolling":true},"title_label":{"type":"label","size":["default","default"],"text":"permissions.title","color":"$title_text_color","layer":3},"permissions_custom_radio_visuals_hover@settings_common.radio_visuals":{"$radio_texture":"textures/ui/permissions_custom_dots_hover"},"permissions_options_panel":{"size":["100%","100%c"],"type":"panel","controls":[{"inner_permissions_options_panel":{"size":["100% - 20px","100%c"],"type":"panel","controls":[{"permissions_options_stack_panel@permissions.permissions_options_stack_panel":{}}]}}]},"radio_title_and_icon":{"type":"panel","$alpha|default":1.0,"controls":[{"radio_icon":{"type":"image","alpha":"$alpha","size":[10,10],"texture":"$radio_texture","anchor_from":"left_middle","anchor_to":"left_middle"}},{"radio_title":{"anchor_from":"left_middle","text":"$radio_label_text","bindings":"$radio_label_bindings","type":"label","alpha":"$alpha","size":["100% - 16px","default"],"offset":[16,0.5],"anchor_to":"left_middle","color":"$radio_label_color"}}],"$radio_label_bindings|default":[],"$radio_label_color|default":"$main_header_text_color","size":["100%",16]}}