{"share_popup_dialog_header":{"type":"panel","anchor_from":"top_left","size":["100%","15%"],"anchor_to":"top_left","controls":[{"share_popup_dialog_header_text@realms_allowlist.share_popup_dialog_header_text":{}},{"close_button@common.close_button":{"anchor_to":"top_right","button_mappings":[{"from_button_id":"button.menu_select","to_button_id":"button.realms_invite_share_close","mapping_type":"pressed"},{"from_button_id":"button.menu_ok","to_button_id":"button.realms_invite_share_close","mapping_type":"focused"}],"offset":[-1,1],"anchor_from":"top_right"}}],"layer":1},"popup_dialog__share_by_link@popup_dialog.modal_input_panel":{"size":["100%","100%"],"controls":[{"share_popup_background@realms_allowlist.share_popup_background":{}},{"gamepad_helpers@common.gamepad_helpers_a_and_b":{"anchor_to":"bottom_middle","offset":[0,"31px"],"anchor_from":"bottom_middle"}},{"share_popup_content@realms_allowlist.share_popup_content":{"layer":1}}]},"uninvited_factory_linked_account@realms_allowlist.linked_account_panel_factory":{"$collection_binding_name":"uninvited_friends_collection"},"share_popup_text":{"text":"$text","text_alignment":"center","type":"label","anchor_from":"center","size":["70%","default"],"anchor_to":"center","shadow":false,"color":"$light_glyph_default_color"},"uninvited_factory_xbl_profile@realms_allowlist.xbl_profile_panel_factory":{"$collection_binding_name":"uninvited_friends_collection"},"copy_button@common_buttons.light_text_button":{"anchor_from":"center","$button_text":"realmsInvitationScreen.shareDialogCopyButton","button_mappings":[{"from_button_id":"button.menu_select","to_button_id":"button.realms_invite_copy","mapping_type":"pressed"},{"from_button_id":"button.menu_ok","to_button_id":"button.realms_invite_copy","mapping_type":"focused"}],"size":[56,28],"anchor_to":"center"},"right_settings_panel":{"controls":[{"member_settings@realms_allowlist.member_settings":{}}],"size":["100%c",21],"type":"stack_panel","orientation":"horizontal"},"share_popup_background":{"type":"image","alpha":0.6,"size":["100%","100%"],"texture":"textures/ui/control","anchor_from":"top_left","anchor_to":"top_left"},"share_popup_dialog_header_text":{"offset":[0,2],"anchor_to":"center","type":"label","anchor_from":"center","font_size":"normal","text":"$text","variables":[{"$text":"realmsInvitationScreen.shareCodeToRealm","requires":"$is_console"},{"$text":"realmsInvitationScreen.shareLinkToRealm","requires":"(not $is_console)"}],"color":"$title_text_color"},"find_friends_button_panel":{"type":"panel","anchor_from":"left_middle","size":["fill",32],"anchor_to":"left_middle","controls":[{"find_friends_button@find_friends_button":{}}]},"cancel_button@common_buttons.light_text_button":{"anchor_from":"bottom_right","$button_text":"realmsInvitationScreen.shareDialogCancel","button_mappings":[{"from_button_id":"button.menu_select","to_button_id":"button.realms_invite_cancel","mapping_type":"pressed"},{"from_button_id":"button.menu_cancel","to_button_id":"button.realms_invite_cancel","mapping_type":"global"},{"from_button_id":"button.menu_ok","to_button_id":"button.realms_invite_cancel","mapping_type":"focused"}],"size":["50% - 2px","90%"],"anchor_to":"bottom_right"},"share_popup_content":{"$share_popup_content_size|default":[340,140],"type":"panel","controls":[{"popup_dialog_bg@realms_common.popup_dialog_bg":{}},{"share_popup_dialog_header@realms_allowlist.share_popup_dialog_header":{}},{"share_popup_dialog_upper_body@realms_allowlist.share_popup_dialog_upper_body":{}},{"share_popup_dialog_lower_body@realms_allowlist.share_popup_dialog_lower_body":{}}],"variables":[{"requires":"$is_console","$share_popup_content_size":[255,140]}],"size":"$share_popup_content_size"},"xbl_profile_blocked_panel_factory@realms_allowlist.gapped_blocked_xbl_profile_panel":{"$blocked_players_collection_name":"blocked_players_collection","$member_collection_name":"members_collection","$uninvited_collection_name":"uninvited_friends_collection","$invited_collection_name":"invited_friends_collection"},"lower_body_default_content":{"type":"panel","anchor_from":"top_middle","size":["100%","90%"],"anchor_to":"top_middle","controls":[{"info_text@realms_allowlist.share_popup_text":{"variables":[{"$text":"realmsInvitationScreen.shareInfoMessageCode","requires":"$is_console"},{"$text":"realmsInvitationScreen.shareInfoMessage","requires":"(not $is_console)"}]}}]},"empty_image":{"type":"image"},"player_online_icon":{"size":[7,7],"texture":"textures/ui/player_online_icon","type":"image"},"transparent_close_button@common_buttons.transparent_content_button":{"$default_pressed_alpha":0,"$pressed_button_texture":"textures/ui/imagetaggedcorner","anchor_from":"top_left","$close_button_to_button_id|default":"button.menu_exit","$default_content_alpha":0,"bindings":[{"binding_name":"(not #gamepad_helper_visible)","binding_name_override":"#visible"}],"anchor_to":"top_left","$default_hover_alpha":0,"size":["100%","100%"],"button_mappings":[{"from_button_id":"button.menu_select","to_button_id":"button.realms_options_close","mapping_type":"pressed"},{"from_button_id":"button.menu_ok","to_button_id":"button.realms_options_close","mapping_type":"focused"}],"$hover_button_texture":"textures/ui/imagetaggedcorner","$default_button_alpha":0},"account_link_image":{"type":"image","texture":"textures/ui/control"},"linked_account_blocked_panel@realms_common.main_banner":{"size":["100%",52],"anchor_to":"top_left","controls":[{"linked_account_positioning_panel@realms_allowlist.linked_user_stack_panel":{"$ignore_status_icon":true}},{"unblock_button@unblock_button":{"anchor_to":"top_right","offset":[-3,3],"anchor_from":"top_right"}},{"progress@progress.progress_loading_bars":{"size":[27,27],"bindings":[{"target_property_name":"#visible","binding_type":"view","resolve_sibling_scope":true,"source_property_name":"(#texture = '')","source_control_name":"gamer_pic"}]}}],"anchor_from":"top_left"},"lower_body_refresh_content":{"type":"panel","anchor_from":"center","size":["100%","80%"],"anchor_to":"center","controls":[{"info_text@realms_allowlist.share_popup_text":{"anchor_from":"top_middle","size":["75%","50% - 2px"],"offset":[0,7],"variables":[{"$text":"realmsInvitationScreen.refreshCodeInfoMessage","requires":"$is_console"},{"$text":"realmsInvitationScreen.refreshLinkInfoMessage","requires":"(not $is_console)"}],"anchor_to":"top_middle"}},{"button_panel":{"type":"panel","anchor_from":"bottom_middle","size":["75%","40%"],"anchor_to":"bottom_middle","offset":[0,-7],"controls":[{"cancel_button@realms_allowlist.cancel_button":{"$button_text":"gui.cancel","anchor_to":"bottom_left","layer":5,"anchor_from":"bottom_left"}},{"new_link_button@realms_allowlist.new_link_button":{}}]}}]},"plus_icon":{"size":[11,11],"texture":"textures/ui/plus","type":"image","layer":2},"permissions_dropdown":{"controls":[{"vertical_space":{"type":"panel","size":[0,2]}},{"option_dropdown_permissions@settings_common.option_dropdown":{"$icon_binding_collection_name_override":"$collection_binding_name","$options_dropdown_toggle_label_binding_collection_name":"$collection_binding_name","$anchor_dropdown_content_from":"top_right","$dropdown_content":"permissions.permission_level_dropdown_content","bindings":[{"binding_type":"collection","binding_name_override":"#visible","binding_collection_name":"$collection_binding_name","binding_name":"#permission_collection_dropdown_visible"}],"$is_world_settings":true,"$dropdown_icon_image_texture_binding":"#collection_permission_level_dropdown_icon_texture","$anchor_dropdown_content_to":"top_right","$content_size":["100% - 9px","100% - 8px"],"$dropdown_name":"player_permissions_dropdown","$options_dropdown_toggle_label_binding_type":"collection","$dropdown_scroll_content_size":["400%","600%"],"$toggle_grid_collection_name":"$collection_binding_name","$icon_binding_type_override":"collection","$button_type_panel":"permissions.permission_level_dropdown_state_content","$options_dropdown_toggle_label_binding":"#player_permissions_dropdown_toggle_label","$dropdown_area":"friends_panel","$content_label_visible":false,"$toggle_binding_type":"collection","$option_enabled_binding_name":"#player_permissions_dropdown_enabled","size":["40px","100%"],"$dropdown_icon_image_size":[10,10],"$show_option_label":false,"$option_dropdown_size":["100%","21px"]}}],"size":["100%c","100%"],"type":"stack_panel","orientation":"vertical"},"friends_containing_panel":{"size":["100%","100%c"],"type":"panel","controls":[{"friends_panel@realms_allowlist.friends_panel":{}}]},"xbl_profile_panel_factory@realms_allowlist.gapped_xbl_profile_panel":{"$blocked_players_collection_name":"blocked_players_collection","$member_collection_name":"members_collection","$uninvited_collection_name":"uninvited_friends_collection","$invited_collection_name":"invited_friends_collection"},"friends_panel":{"$member_collection_name":"members_collection","anchor_from":"top_left","orientation":"vertical","anchor_to":"top_left","type":"stack_panel","size":"$friend_panel_size","controls":[{"add_friends_and_invite_link_panel@realms_allowlist.add_friends_and_invite_link_panel":{}},{"option_dropdown_permissions@settings_common.option_dropdown":{"$dropdown_area":"friends_panel","$dropdown_scroll_content_size":["100%","385%"],"$button_type_panel":"permissions.permission_level_dropdown_state_content","$option_label":"permissions.title.settings","$dropdown_content":"permissions.permission_level_dropdown_content","bindings":[{"binding_name":"#permission_dropdown_visible","binding_name_override":"#visible"}],"$is_world_settings":true,"$options_dropdown_toggle_label_binding":"#realm_default_permission_dropdown_toggle_label","size":["100%","50px"],"$dropdown_name":"realm_default_permission_dropdown","$show_option_label":true,"$option_enabled_binding_name":"#realm_default_permission_dropdown_enabled"}},{"player_filter_label@realms_allowlist.player_filter_label":{}},{"player_filter_text_box@realms_allowlist.player_filter_text_box":{}},{"spacing_gap_members_top@realms_allowlist.spacing_gap":{}},{"members_label@realms_allowlist.members_label":{}},{"members_stack@realms_allowlist.factory_stack":{"bindings":[{"binding_name":"#members_section_content","binding_name_override":"#collection_length"}],"factory":{"name":"factory","control_ids":{"large_button":"@realms_allowlist.member_factory_linked_account","small_button":"@realms_allowlist.member_factory_xbl_profile"}},"collection_name":"members_collection"}},{"spacing_gap_members_bottom@realms_allowlist.spacing_gap":{}},{"members_page_panel@realms_allowlist.page_panel":{"$is_next_visible":"#members_nextButton_visible","$prev_button_name":"prev_page_button_members","$is_prev_visible":"#members_prevButton_visible","$next_button_name":"next_page_button_members","$this_page_index_text":"#members_page_index_text","$is_visible_binding_name":"#members_buttons_visible"}},{"invited_friends_label@realms_allowlist.invited_friends_label":{}},{"invited_stack@realms_allowlist.factory_stack":{"bindings":[{"binding_name":"#invited_section_content","binding_name_override":"#collection_length"}],"factory":{"name":"factory","control_ids":{"large_button":"@realms_allowlist.invited_factory_linked_account","small_button":"@realms_allowlist.invited_factory_xbl_profile"}},"collection_name":"invited_friends_collection"}},{"spacing_gap_invited_friends@realms_allowlist.spacing_gap":{}},{"invited_friends_page_panel@realms_allowlist.page_panel":{"$is_next_visible":"#invited_friends_nextButton_visible","$prev_button_name":"prev_page_button_invited_friends","$is_prev_visible":"#invited_friends_prevButton_visible","$next_button_name":"next_page_button_invited_friends","$this_page_index_text":"#invited_friends_page_index_text","$is_visible_binding_name":"#invited_friends_buttons_visible"}},{"uninvited_friends_label@realms_allowlist.uninvited_friends_label":{}},{"uninvited_stack@realms_allowlist.factory_stack":{"bindings":[{"binding_name":"#uninvited_section_content","binding_name_override":"#collection_length"}],"factory":{"name":"factory","control_ids":{"large_button":"@realms_allowlist.uninvited_factory_linked_account","small_button":"@realms_allowlist.uninvited_factory_xbl_profile"}},"collection_name":"uninvited_friends_collection"}},{"spacing_gap_uninvited_friends@realms_allowlist.spacing_gap":{}},{"uninvited_friends_page_panel@realms_allowlist.page_panel":{"$is_next_visible":"#uninvited_friends_nextButton_visible","$prev_button_name":"prev_page_button_uninvited_friends","$is_prev_visible":"#uninvited_friends_prevButton_visible","$next_button_name":"next_page_button_uninvited_friends","$this_page_index_text":"#uninvited_friends_page_index_text","$is_visible_binding_name":"#uninvited_friends_buttons_visible"}},{"blocked_players_label@realms_allowlist.blocked_players_label":{}},{"blocked_players_stack@realms_allowlist.factory_stack":{"bindings":[{"binding_name":"#blocked_section_content","binding_name_override":"#collection_length"}],"factory":{"name":"factory","control_ids":{"large_button":"@realms_allowlist.blocked_factory_linked_account","small_button":"@realms_allowlist.blocked_factory_xbl_profile"}},"collection_name":"blocked_players_collection"}},{"spacing_gap_blocked_players@realms_allowlist.spacing_gap":{}},{"blocked_players_page_panel@realms_allowlist.page_panel":{"$is_next_visible":"#blocked_players_nextButton_visible","$prev_button_name":"prev_page_button_blocked_players","$is_prev_visible":"#blocked_players_prevButton_visible","$next_button_name":"next_page_button_blocked_players","$this_page_index_text":"#blocked_players_page_index_text","$is_visible_binding_name":"#blocked_players_buttons_visible"}},{"no_invites_label@realms_allowlist.no_invites_label":{}},{"loading_friends@realms_allowlist.loading_friends":{}}],"$blocked_players_collection_name":"blocked_players_collection","$uninvited_collection_name":"uninvited_friends_collection","$invited_collection_name":"invited_friends_collection"},"refresh_button@common_buttons.transparent_content_button":{"$default_pressed_alpha":0.6,"$light_glyph_pressed_color":[0.8,0.84,0.93],"$button_content":"realms_allowlist.refresh_icon","anchor_from":"left_middle","anchor_to":"left_middle","$default_button_alpha":0.3,"$light_glyph_default_color":[1,1,1],"bindings":[{"binding_name":"#members_list_enabled","binding_name_override":"#enabled"}],"offset":[4,0],"$default_hover_alpha":0.45,"$light_glyph_hover_color":[1.19,1.14,1.05],"$button_pressed_offset":[0,0],"size":[21,21],"button_mappings":[{"from_button_id":"button.menu_select","to_button_id":"button.realms_invite_refresh","mapping_type":"pressed"},{"from_button_id":"button.menu_ok","to_button_id":"button.realms_invite_refresh","mapping_type":"focused"}]},"blocked_factory_xbl_profile@realms_allowlist.xbl_profile_blocked_panel_factory":{"$collection_binding_name":"blocked_players_collection"},"gamerpic_panel":{"type":"panel","anchor_from":"left_middle","size":[21,21],"anchor_to":"left_middle","controls":[{"black_border@realms_allowlist.black_border":{}},{"gamer_pic@realms_allowlist.gamer_pic":{"size":["100% - 2px","100% - 2px"],"layer":1}}]},"player_filter_text_box@common.text_edit_box":{"$text_box_name":"#player_filter_text_box","max_length":30,"size":["100%",25],"$place_holder_text":"realmsSettingsScreen.searchBox"},"linked_account_panel@realms_common.main_banner":{"size":["100%",52],"anchor_to":"top_left","controls":[{"linked_account_positioning_panel@realms_allowlist.linked_user_stack_panel":{}},{"right_controls_panel@realms_allowlist.right_controls_panel":{"offset":[-3,-12],"layer":6}},{"progress@progress.progress_loading_bars":{"size":[27,27],"bindings":[{"target_property_name":"#visible","binding_type":"view","resolve_sibling_scope":true,"source_property_name":"(#texture = '')","source_control_name":"gamer_pic"}]}}],"anchor_from":"top_left"},"black_border":{"type":"image","texture":"textures/ui/mainbanners"},"xbl_profile_panel@realms_common.main_banner":{"size":["100%",27],"anchor_to":"top_left","controls":[{"player_status_panel@realms_allowlist.player_status_panel":{}},{"xbl_user_panel@realms_allowlist.xbl_user_panel":{}},{"right_controls_panel@realms_allowlist.right_controls_panel":{"offset":[-3,0],"layer":6}},{"progress@progress.progress_loading_bars":{"size":[27,27],"bindings":[{"target_property_name":"#visible","binding_type":"view","resolve_sibling_scope":true,"source_property_name":"(#texture = '')","source_control_name":"gamer_pic"}]}}],"anchor_from":"top_left"},"link_url_text":{"$link_url_text_size|default":[208,"default"],"anchor_from":"left_middle","bindings":[{"binding_name":"#linkurl","binding_type":"global"}],"anchor_to":"left_middle","variables":[{"$link_url_text_size":[163,"default"],"requires":"$is_console"}],"layer":1,"hide_hyphen":true,"text_alignment":"center","type":"label","text":"#linkurl","size":"$link_url_text_size","offset":[27,0],"font_size":"normal","color":"$body_text_color"},"linked_profile_pictures_panel":{"type":"stack_panel","anchor_from":"center","size":[21,"100%"],"anchor_to":"center","orientation":"vertical","controls":[{"pp2@realms_allowlist.third_party_profile_pic_panel":{"size":["100%",21],"layer":1}},{"account_link@realms_allowlist.account_link_icon":{"size":["100%","fill"]}},{"pp1@realms_allowlist.gamerpic_panel":{"size":["100%",21],"layer":1}}]},"uninvited_friends_label":{"bindings":[{"binding_name_override":"#visible","binding_name":"#uninvited_friends_visible","binding_type":"global"}],"type":"panel","anchor_from":"top_left","size":["100%",11],"anchor_to":"top_left","controls":[{"friend_title":{"color":"$main_header_text_color","text":"realmsInvitationScreen.friends","type":"label","anchor_from":"bottom_left","font_size":"normal","anchor_to":"bottom_left","offset":[1,-1],"layer":1}}]},"new_link_button@common_buttons.light_text_button":{"anchor_from":"bottom_right","size":["50% - 2px","90%"],"button_mappings":[{"from_button_id":"button.menu_select","to_button_id":"button.realms_invite_new_link","mapping_type":"pressed"},{"from_button_id":"button.menu_ok","to_button_id":"button.realms_invite_new_link","mapping_type":"focused"}],"variables":[{"$button_text":"realmsInvitationScreen.shareDialogNewCodeButton","requires":"$is_console"},{"$button_text":"realmsInvitationScreen.shareDialogNewLinkButton","requires":"(not $is_console)"}],"anchor_to":"bottom_right"},"options_popup_dialog_button_panel":{"size":["20%","15%"],"type":"stack_panel","anchor_from":"top_right","orientation":"vertical","offset":[-20,60],"anchor_to":"top_right","controls":[{"transparent_close_button_inline@realms_allowlist.transparent_close_button":{"anchor_from":"top_right","size":[1,1],"offset":[30,0],"anchor_to":"top_right","tts_name":"accessibility.button.close"}},{"clear_members_button@common_buttons.light_text_button":{"bindings":[{"binding_name":"#members_list_enabled","binding_name_override":"#enabled"}],"anchor_to":"left_middle","anchor_from":"left_middle","size":["default",30],"button_mappings":[{"from_button_id":"button.menu_select","to_button_id":"button.clear_members","mapping_type":"pressed"},{"from_button_id":"button.menu_ok","to_button_id":"button.clear_members","mapping_type":"focused"}],"$button_text":"realmsClearMembers.clear","layer":2}}]},"share_by_link_button@common_buttons.light_text_button":{"bindings":[{"binding_name":"#members_list_enabled","binding_name_override":"#enabled"}],"anchor_to":"right_middle","anchor_from":"right_middle","size":["100%",30],"button_mappings":[{"from_button_id":"button.menu_select","to_button_id":"button.realms_invite_share_by_link","mapping_type":"pressed"},{"from_button_id":"button.menu_ok","to_button_id":"button.realms_invite_share_by_link","mapping_type":"focused"}],"variables":[{"$button_text":"realmsInvitationScreen.shareByCode","requires":"$is_console"},{"$button_text":"realmsInvitationScreen.shareByLink","requires":"(not $is_console)"}],"layer":2},"spacing_gap":{"type":"panel","size":["100%",5]},"third_party_profile_pic_panel":{"type":"panel","anchor_from":"left_middle","size":["100%","100%"],"anchor_to":"left_middle","controls":[{"black_border@realms_allowlist.black_border":{}},{"third_party_profile_picture@realms_allowlist.third_party_profile_picture":{"size":["100% - 2px","100% - 2px"],"layer":1}}]},"third_party_user_panel":{"orientation":"horizontal","bindings":[{"target_property_name":"#visible","binding_type":"view","resolve_sibling_scope":true,"source_property_name":"(not (#texture = ''))","source_control_name":"third_party_profile_picture"}],"type":"stack_panel","anchor_from":"left_middle","controls":[{"spacing1@realms_allowlist.horizontal_indent":{"size":[25,"100%"]}},{"profile_picture@realms_allowlist.third_party_profile_pic_panel":{"size":[21,"100%"]}},{"spacing2@realms_allowlist.horizontal_indent":{"size":[1,"100%"]}},{"third_party_profile_label@realms_allowlist.third_party_profile_label":{}}],"anchor_to":"left_middle","size":["100%c","100% - 6px"],"layer":6},"unblock_button@common_buttons.light_content_button":{"bindings":[{"binding_collection_name":"$collection_binding_name","binding_type":"collection_details"},{"binding_name":"#members_list_enabled","binding_name_override":"#enabled"}],"$button_content":"realms_allowlist.unblock_label","anchor_from":"right_middle","size":[62,21],"anchor_to":"right_middle","button_mappings":[{"from_button_id":"button.menu_select","to_button_id":"button.realms_invite_unblock","mapping_type":"pressed"},{"from_button_id":"button.menu_ok","to_button_id":"button.realms_invite_unblock","mapping_type":"focused"}]},"popup_dialog__options@popup_dialog.modal_input_panel":{"size":["100%","100%"],"controls":[{"transparent_close_button@realms_allowlist.transparent_close_button":{"focus_enabled":false,"tts_ignore_count":true}},{"options_popup_dialog_button_panel@realms_allowlist.options_popup_dialog_button_panel":{}}]},"gapped_blocked_linked_account_panel@factory_gap_template":{"$templated_control":"realms_allowlist.linked_account_blocked_panel"},"invited_factory_linked_account@realms_allowlist.linked_account_panel_factory":{"$collection_binding_name":"invited_friends_collection"},"invite_button@common_buttons.light_text_button":{"layer":1,"bindings":[{"binding_collection_name":"$collection_binding_name","binding_type":"collection_details"},{"binding_name":"#invite_button_visible","binding_name_override":"#visible","binding_collection_name":"$collection_binding_name","binding_type":"collection"},{"binding_name":"#members_list_enabled","binding_name_override":"#enabled"}],"$button_text":"realmsSettingsScreen.allowlist_invite","anchor_from":"left_middle","size":[21,21],"button_mappings":[{"from_button_id":"button.menu_select","to_button_id":"button.realms_invite_plus","mapping_type":"pressed"},{"from_button_id":"button.menu_ok","to_button_id":"button.realms_invite_plus","mapping_type":"focused"}],"anchor_to":"left_middle","ignored":"($collection_binding_name = $member_collection_name or $collection_binding_name = $invited_collection_name)"},"player_filter_label":{"type":"panel","anchor_from":"top_left","size":["100%",13],"anchor_to":"top_left","controls":[{"player_filter_title":{"color":"$main_header_text_color","text":"realmsInvitationScreen.playerFilterTitle","type":"label","anchor_from":"bottom_left","font_size":"normal","anchor_to":"bottom_left","offset":[1,-1],"layer":1}}]},"loading_friends@realms_allowlist.panel_text":{"bindings":[{"binding_name_override":"#visible","binding_name":"#loading_friends","binding_type":"global"}],"anchor_from":"center","font_size":"normal","text":"realmsInvitationScreen.loadingFriends","size":["100%",20],"anchor_to":"center"},"gapped_linked_account_panel@factory_gap_template":{"$templated_control":"realms_allowlist.linked_account_panel"},"gamertag_label_panel":{"type":"panel","anchor_from":"left_middle","size":[100,"100%"],"anchor_to":"left_middle","controls":[{"gamertag_label@realms_allowlist.gamertag_label":{}},{"real_name_label@realms_allowlist.real_name_label":{}}]},"share_by_link_button_panel":{"type":"panel","anchor_from":"right_middle","size":["fill",32],"anchor_to":"right_middle","controls":[{"share_by_link_button@realms_allowlist.share_by_link_button":{}}]},"linked_account_panel_factory@realms_allowlist.gapped_linked_account_panel":{"$blocked_players_collection_name":"blocked_players_collection","$member_collection_name":"members_collection","$uninvited_collection_name":"uninvited_friends_collection","$invited_collection_name":"invited_friends_collection"},"share_button@common_buttons.light_glyph_button":{"$light_glyph_pressed_color":[0.9,0.9,0.9],"anchor_from":"right_middle","anchor_to":"right_middle","bindings":[{"binding_name":"#copy_share_enabled","binding_name_override":"#enabled"}],"size":[28,28],"$light_glyph_default_color":[1,1,1],"button_mappings":[{"from_button_id":"button.menu_select","to_button_id":"button.realms_invite_share","mapping_type":"pressed"},{"from_button_id":"button.menu_ok","to_button_id":"button.realms_invite_share","mapping_type":"focused"}],"$light_glyph_hover_color":[1,1,1],"offset":[-26,0]},"real_name_label@realms_allowlist.panel_text":{"bindings":[{"binding_type":"collection","binding_name":"#real_name","binding_collection_name":"$collection_binding_name"}],"anchor_from":"bottom_left","font_size":"normal","text":"#real_name","anchor_to":"bottom_left","offset":[1,"100%"]},"gapped_blocked_xbl_profile_panel@factory_gap_template":{"$templated_control":"realms_allowlist.blocked_panel"},"blocked_players_label":{"bindings":[{"binding_name_override":"#visible","binding_name":"#blocked_players_visible","binding_type":"global"}],"type":"panel","anchor_from":"top_left","size":["100%",11],"anchor_to":"top_left","controls":[{"friend_title":{"color":"$main_header_text_color","text":"realmsInvitationScreen.blocked","type":"label","anchor_from":"bottom_left","font_size":"normal","anchor_to":"bottom_left","offset":[1,-1],"layer":1}}]},"refresh_icon":{"texture":"textures/ui/refresh_light","type":"image","layer":2},"member_factory_linked_account@realms_allowlist.linked_account_panel_factory":{"$collection_binding_name":"members_collection"},"vertical_indent":{"type":"panel","size":["100%",2]},"factory_stack":{"type":"stack_panel","anchor_from":"top_middle","orientation":"vertical","anchor_to":"top_middle","size":["100%","100%c"]},"member_settings":{"bindings":[{"binding_type":"collection","binding_name_override":"#visible","binding_collection_name":"$collection_binding_name","binding_name":"#show_member_settings"}],"type":"stack_panel","controls":[{"minus_button@realms_allowlist.minus_button":{}},{"horizontal_space":{"type":"panel","size":[2,"100%"]}},{"member_permissions@realms_allowlist.permissions_dropdown":{}},{"op_deop_button@realms_allowlist.op_deop_button":{"bindings":[{"binding_type":"collection","binding_name_override":"#visible","binding_collection_name":"$collection_binding_name","binding_name":"(not #permission_collection_dropdown_visible)"}]}}],"size":["100%c",21],"orientation":"horizontal","ignored":"($collection_binding_name = $uninvited_collection_name)"},"third_party_profile_name_label@realms_allowlist.panel_text":{"bindings":[{"binding_type":"collection","binding_name":"#third_party_profile_name","binding_collection_name":"$collection_binding_name"}],"anchor_from":"top_left","font_size":"normal","text":"#third_party_profile_name","anchor_to":"top_left","offset":[1,1]},"realms_allowlist_panel_content@common.scrolling_panel":{"$scroll_size":[5,"100% - 4px"],"$show_background":false,"anchor_from":"top_left","anchor_to":"top_left","$scrolling_content":"realms_allowlist.friends_containing_panel","$friend_panel_size":["100% - 1px","100%c"]},"account_link_icon":{"controls":[{"space_01":{"type":"panel","size":[9,"100%"]}},{"account_link_image@invite.account_link_image":{"size":[2,"100%"]}},{"space_03":{"type":"panel","size":[9,"100%"]}}],"size":["100%","100%"],"type":"stack_panel","orientation":"horizontal"},"linked_account_blocked_panel_factory@realms_allowlist.gapped_blocked_linked_account_panel":{"$blocked_players_collection_name":"blocked_players_collection","$member_collection_name":"members_collection","$uninvited_collection_name":"uninvited_friends_collection","$invited_collection_name":"invited_friends_collection"},"third_party_profile_label":{"type":"panel","anchor_from":"left_middle","size":[100,"100%"],"anchor_to":"left_middle","controls":[{"profile_name_label@realms_allowlist.third_party_profile_name_label":{}}]},"minus_button@common_buttons.light_glyph_button":{"bindings":[{"binding_collection_name":"$collection_binding_name","binding_type":"collection_details"},{"binding_name":"#members_list_enabled","binding_name_override":"#enabled"}],"$button_content":"realms_allowlist.minus_icon","anchor_from":"left_middle","size":[21,21],"anchor_to":"left_middle","button_mappings":[{"from_button_id":"button.menu_select","to_button_id":"button.realms_invite_minus","mapping_type":"pressed"},{"from_button_id":"button.menu_ok","to_button_id":"button.realms_invite_minus","mapping_type":"focused"}],"layer":2},"share_popup_dialog_lower_body":{"controls":[{"default@realms_allowlist.lower_body_default_content":{"bindings":[{"binding_name":"#default_message_visible","binding_name_override":"#visible"}]}},{"refresh@realms_allowlist.lower_body_refresh_content":{"bindings":[{"binding_name":"#refresh_message_visible","binding_name_override":"#visible"}]}}],"type":"panel","anchor_from":"top_left","size":["100%","65%"],"anchor_to":"top_left","offset":[0,"40%"],"layer":1},"horizontal_indent":{"type":"panel","size":[2,"100%"]},"player_status_panel":{"type":"panel","anchor_from":"left_middle","size":[20,"100% - 2px"],"anchor_to":"left_middle","controls":[{"player_online_icon@realms_allowlist.player_online_icon":{"bindings":[{"binding_type":"collection","binding_name_override":"#visible","binding_collection_name":"$collection_binding_name","binding_name":"#player_online"}]}},{"player_offline_icon@realms_allowlist.player_offline_icon":{"bindings":[{"binding_type":"collection","binding_name_override":"#visible","binding_collection_name":"$collection_binding_name","binding_name":"(not #player_online)"}]}}],"layer":6},"op_icon":{"size":[14,14],"texture":"textures/ui/op","type":"image","layer":2},"unblock_label":{"anchor_to":"center","text_alignment":"center","type":"label","anchor_from":"center","size":["100%",15],"offset":[0,2],"text":"realmsInvitationScreen.unblock","color":"$text_color"},"gapped_xbl_profile_panel@factory_gap_template":{"$templated_control":"realms_allowlist.xbl_profile_panel"},"find_friends_button@common_buttons.light_text_button":{"anchor_to":"left_middle","bindings":[{"binding_name":"#members_list_enabled","binding_name_override":"#enabled"}],"$button_content":"realms_allowlist.plus_icon","anchor_from":"left_middle","size":["100%",30],"button_mappings":[{"from_button_id":"button.menu_select","to_button_id":"button.realms_invite_find_friends","mapping_type":"pressed"},{"from_button_id":"button.menu_ok","to_button_id":"button.realms_invite_find_friends","mapping_type":"focused"}],"$button_text":"realmsInvitationScreen.findFriends","layer":2},"realms_allowlist_content_panel_children":{"controls":[{"realms_allowlist_panel_content@realms_allowlist.realms_allowlist_panel_content":{"$scrolling_pane_size":["100% - 4px","100%"],"offset":[2,0]}},{"done_button@common_buttons.light_text_button":{"$button_text":"realmsInvitationScreen.done","anchor_to":"top_middle","anchor_from":"bottom_middle","size":["100% + 2px",30],"button_mappings":[{"from_button_id":"button.menu_select","to_button_id":"button.menu_realm_send_invites","mapping_type":"pressed"},{"from_button_id":"button.menu_ok","to_button_id":"button.menu_realm_send_invites","mapping_type":"focused"}],"offset":[0,5],"layer":2}}],"anchor_to":"top_left","type":"panel","anchor_from":"top_left"},"page_panel":{"size":["100%",20],"bindings":[{"binding_name_override":"#visible","binding_name":"$is_visible_binding_name","binding_type":"global"}],"type":"panel","controls":[{"prev_button@settings_common.action_button":{"bindings":[{"binding_name":"$is_prev_visible","binding_name_override":"#visible"}],"anchor_from":"top_left","$is_prev_visible|default":"#visible","$button_text":"realmsSettingsScreen.dev_prev_page_label","anchor_to":"top_left","size":[70,"100%"],"$pressed_button_name":"$prev_button_name"}},{"page_text":{"bindings":[{"binding_name":"$this_page_index_text"}],"type":"label","anchor_from":"center","size":["default","50%"],"text":"$this_page_index_text","anchor_to":"center","color":"$sub_header_text_color"}},{"next_button@settings_common.action_button":{"$is_next_visible|default":"#visible","bindings":[{"binding_name":"$is_next_visible","binding_name_override":"#visible"}],"$pressed_button_name":"$next_button_name","$button_text":"realmsSettingsScreen.dev_next_page_label","anchor_to":"top_right","anchor_from":"top_right","size":[70,"100%"]}}]},"third_party_profile_picture":{"texture_file_system":"#texture_file_system","texture":"#texture","type":"image","bindings":[{"binding_type":"collection","binding_name_override":"#texture","binding_collection_name":"$collection_binding_name","binding_name":"#third_party_profile_pic"},{"binding_type":"collection","binding_name_override":"#texture_file_system","binding_collection_name":"$collection_binding_name","binding_name":"#third_party_profile_pic_file_system"}]},"blocked_factory_linked_account@realms_allowlist.linked_account_blocked_panel_factory":{"$collection_binding_name":"blocked_players_collection"},"blocked_panel@realms_common.main_banner":{"size":["100%",27],"anchor_to":"top_left","controls":[{"xbl_user_panel@realms_allowlist.xbl_user_panel":{}},{"unblock_button@unblock_button":{"offset":[-3,0]}}],"anchor_from":"top_left"},"gamer_pic":{"texture_file_system":"#texture_file_system","texture":"#texture","type":"image","bindings":[{"binding_type":"collection","binding_name_override":"#texture","binding_collection_name":"$collection_binding_name","binding_name":"#gamerpic_texture"},{"binding_type":"collection","binding_name_override":"#texture_file_system","binding_collection_name":"$collection_binding_name","binding_name":"#gamerpic_texture_file_system"}]},"member_factory_xbl_profile@realms_allowlist.xbl_profile_panel_factory":{"$collection_binding_name":"members_collection"},"namespace":"realms_allowlist","op_deop_button@common_toggles.light_image_toggle_collection":{"$toggle_enabled_binding_name":"#members_list_enabled","$toggle_name":"#operator","$toggle_enabled_binding_type":"global","anchor_to":"left_middle","layer":2,"anchor_from":"left_middle","$unchecked_image":"realms_allowlist.deop_icon","$toggle_binding_type":"collection","$checked_image":"realms_allowlist.op_icon","size":[21,21],"$toggle_state_binding_name":"#operator","$toggle_grid_collection_name":"$collection_binding_name","ignored":"($collection_binding_name = $uninvited_collection_name)"},"invited_friends_label":{"bindings":[{"binding_name_override":"#visible","binding_name":"#invited_friends_visible","binding_type":"global"}],"type":"panel","anchor_from":"top_left","size":["100%",13],"anchor_to":"top_left","controls":[{"friend_title":{"color":"$main_header_text_color","text":"realmsInvitationScreen.invitedFriends","type":"label","anchor_from":"bottom_left","font_size":"normal","anchor_to":"bottom_left","offset":[1,-1],"layer":1}}]},"panel_text":{"type":"label","anchor_from":"top_left","color":"$dark_grid_item_text_color","anchor_to":"top_left","shadow":false,"layer":5},"xbl_user_panel":{"orientation":"horizontal","bindings":[{"target_property_name":"#visible","binding_type":"view","resolve_sibling_scope":true,"source_property_name":"(not (#texture = ''))","source_control_name":"gamer_pic"}],"type":"stack_panel","anchor_from":"left_middle","controls":[{"spacing1@realms_allowlist.horizontal_indent":{"size":[25,"100%"]}},{"platform_icon_positioner":{"size":[15,"100%"],"type":"panel","ignored":"(not $is_ps4)"}},{"gamerpic_panel@realms_allowlist.gamerpic_panel":{"size":[21,"100%"]}},{"spacing2@realms_allowlist.horizontal_indent":{"size":[1,"100%"]}},{"gamertag_label_panel@realms_allowlist.gamertag_label_panel":{}}],"anchor_to":"left_middle","size":["100%c","100% - 6px"],"layer":6},"linked_user_stack_panel":{"$ignore_status_icon|default":false,"anchor_from":"left_middle","orientation":"horizontal","anchor_to":"left_middle","layer":6,"bindings":[{"target_property_name":"#visible","binding_type":"view","resolve_sibling_scope":true,"source_property_name":"(not (#texture = ''))","source_control_name":"third_party_profile_picture"},{"target_property_name":"#visible","binding_type":"view","resolve_sibling_scope":true,"source_property_name":"(not (#texture = ''))","source_control_name":"gamer_pic"}],"type":"stack_panel","size":["100%","100% - 6px"],"controls":[{"allow_offset_control":{"size":[20,"100%"],"type":"panel","controls":[{"player_status_panel@realms_allowlist.player_status_panel":{"size":[20,20],"anchor_to":"top_left","ignored":"$ignore_status_icon","anchor_from":"top_left"}}]}},{"platform_icon_positioner":{"size":[15,"100%"],"type":"panel","controls":[{"platform_icon@invite.platform_icon_panel":{"$is_platform_icon":"$invite_platform_icons_visible","layer":1,"anchor_to":"top_left","anchor_from":"top_left","$icon_offset":[0,2]}}]}},{"spacing1@realms_allowlist.horizontal_indent":{"size":[5,"100%"]}},{"profile_picture@realms_allowlist.linked_profile_pictures_panel":{}},{"spacing2@realms_allowlist.horizontal_indent":{"size":[1,"100%"]}},{"platform_names_label@realms_allowlist.platform_profile_names":{"size":["fill","100%"]}},{"spacing3@realms_allowlist.horizontal_indent":{"size":[3,"100%"]}}]},"platform_profile_names":{"controls":[{"friend_grid_third_party_tag@realms_allowlist.third_party_profile_label":{"size":["100%",12],"layer":1}},{"spacer_02":{"type":"panel","size":["100%",13]}},{"friend_grid_xbl_gamertag@realms_allowlist.gamertag_label_panel":{"size":["100%",12],"layer":1}},{"spacer_03":{"type":"panel","size":["100%",10]}}],"size":["fill","100%"],"type":"stack_panel","orientation":"vertical"},"deop_icon":{"size":[14,14],"texture":"textures/ui/deop","type":"image","layer":2},"invited_factory_xbl_profile@realms_allowlist.xbl_profile_panel_factory":{"$collection_binding_name":"invited_friends_collection"},"link_panel@realms_common.hollow_banner":{"size":["100%-12px","100%"],"anchor_to":"center","controls":[{"refresh_button@realms_allowlist.refresh_button":{}},{"link_url_text@realms_allowlist.link_url_text":{}},{"copy_share_panel":{"offset":[-6,0],"size":["100%c",28],"type":"stack_panel","anchor_from":"right_middle","controls":[{"link_copy@realms_allowlist.copy_button":{"ignored":"(not $supports_clipboard_set)","bindings":[{"binding_name":"#copy_share_enabled","binding_name_override":"#enabled"}]}},{"spacing":{"size":[1,"100%"],"type":"panel","ignored":"(not $supports_share)"}},{"link_share@realms_allowlist.share_button":{"offset":[0,6],"$button_content":"realms_allowlist.share_icon","ignored":"(not $supports_share)"}}],"anchor_to":"right_middle","variables":[{"$share_icon_texture":"textures/ui/share_apple","requires":"($apple_os and $supports_share)","$share_icon_size":[11,15],"$share_icon_offset":[3.5,-1.5]},{"$share_icon_texture":"textures/ui/share_microsoft","requires":"(($microsoft_os or (not $apple_os and not $google_os)) and $supports_share)","$share_icon_size":[15,13],"$share_icon_offset":[2.5,-0.5]},{"$share_icon_texture":"textures/ui/share_google","requires":"($google_os and $supports_share)","$share_icon_size":[14,13],"$share_icon_offset":[2.0,-0.5]}],"orientation":"horizontal"}}],"anchor_from":"center"},"members_label":{"bindings":[{"binding_name_override":"#visible","binding_name":"#members_visible","binding_type":"global"}],"type":"stack_panel","anchor_from":"top_left","orientation":"horizontal","anchor_to":"top_left","size":["100%",13],"controls":[{"friend_title":{"color":"$main_header_text_color","text":"realmsInvitationScreen.members","type":"label","anchor_from":"bottom_left","font_size":"normal","anchor_to":"bottom_left","offset":[1,-1],"layer":1}},{"padding_panel":{"type":"panel","size":["fill","100%"]}},{"loading_text":{"anchor_from":"bottom_right","text":"#member_loading_text","layer":1,"bindings":[{"binding_name":"#member_loading_text","binding_type":"global"}],"type":"label","font_size":"normal","offset":[1,-1],"anchor_to":"bottom_right","color":"$main_header_text_color"}}]},"more_icon":{"size":[13,3],"texture":"textures/ui/more_dots","type":"image","layer":2},"player_offline_icon":{"size":[7,7],"texture":"textures/ui/player_offline_icon","type":"image"},"realms_allowlist_screen@common.base_screen":{"$screen_content":"realms_allowlist.realms_allowlist_content"},"realms_allowlist_content_panel@common_dialogs.main_panel_one_button":{"size":"$narrow_screen_size","$text_name":"realmsInvitationScreen.title","$child_control":"realms_allowlist.realms_allowlist_content_panel_children","$show_close_button":false},"right_controls_panel":{"type":"panel","anchor_from":"right_middle","size":["100%c","100%"],"anchor_to":"right_middle","controls":[{"right_settings_panel@realms_allowlist.right_settings_panel":{}},{"uninvited_friends_invite_button@realms_allowlist.invite_button":{"size":[62,21]}}]},"add_friends_and_invite_link_panel":{"type":"panel","anchor_from":"top_left","size":["100%",40],"anchor_to":"top_left","controls":[{"allowlist_stack_panel":{"controls":[{"find_friends_button_panel@realms_allowlist.find_friends_button_panel":{"ignored":"(not $supports_add_friend)"}},{"spacing":{"type":"panel","size":[2,"100%"]}},{"share_by_link_button_panel@realms_allowlist.share_by_link_button_panel":{}},{"spacing2":{"type":"panel","size":[1,"100%"]}},{"options_panel":{"size":[32,32],"bindings":[{"binding_name_override":"#visible","binding_name":"#options_visible","binding_type":"global"}],"type":"panel","controls":[{"options_button@common_buttons.light_content_button":{"$button_content":"realms_allowlist.options_icon","$pressed_button_name":"button.member_list_options","size":[30,30],"anchor_to":"center","anchor_from":"center","tts_name":"accessibility.dropdown.tts.title"}}]}}],"orientation":"horizontal","type":"stack_panel","size":["100%","100%"]}}]},"factory_gap_template":{"controls":[{"gapped_control@$templated_control":{}},{"spacing1":{"type":"panel","size":["100%",3]}}],"size":["100%","100%c"],"type":"stack_panel","orientation":"vertical"},"realms_allowlist_content":{"type":"panel","controls":[{"root_panel":{"controls":[{"realms_allowlist_content_panel@realms_allowlist.realms_allowlist_content_panel":{"layer":1}}],"anchor_to":"top_left","type":"input_panel","anchor_from":"top_left"}},{"popup_dialog_factory":{"type":"factory","control_ids":{"share_by_link":"@realms_allowlist.popup_dialog__share_by_link"}}},{"popup_dialog_factory_options":{"type":"factory","control_ids":{"options_modal":"@realms_allowlist.popup_dialog__options"}}}]},"gamertag_label@realms_allowlist.panel_text":{"bindings":[{"binding_type":"collection","binding_name":"#gamertag","binding_collection_name":"$collection_binding_name"}],"anchor_from":"top_left","font_size":"normal","text":"#gamertag","anchor_to":"top_left","offset":[1,1]},"blocked_grid_item":{"type":"panel","anchor_from":"top_left","size":["100%",29],"anchor_to":"top_left","controls":[{"blocked_panel@realms_allowlist.blocked_panel":{}}]},"no_invites_label@realms_allowlist.panel_text":{"bindings":[{"binding_name_override":"#visible","binding_name":"#no_invites_visible","binding_type":"global"}],"anchor_from":"center","font_size":"normal","text":"realmsInvitationScreen.noInvites","size":["100%",20],"anchor_to":"center"},"share_popup_dialog_upper_body":{"controls":[{"link_panel@realms_allowlist.link_panel":{}}],"type":"panel","anchor_from":"top_left","size":["100%","30%"],"anchor_to":"top_left","offset":[0,"15%"],"layer":1},"minus_icon":{"size":[11,3],"texture":"textures/ui/minus","type":"image","layer":2},"share_icon":{"type":"image","size":"$share_icon_size","offset":"$share_icon_offset","texture":"$share_icon_texture","layer":2},"options_icon":{"type":"image","size":[11,11],"texture":"textures/ui/more-dots","layer":0,"color":"black"}}