{"pools":[{"entries":[{"type":"item","name":"minecraft:emerald"},{"functions":[{"function":"set_count","count":{"max":3,"min":1}}],"name":"minecraft:porkchop","weight":6,"type":"item"},{"functions":[{"function":"set_count","count":{"max":3,"min":1}}],"name":"minecraft:wheat","weight":6,"type":"item"},{"functions":[{"function":"set_count","count":{"max":3,"min":1}}],"name":"minecraft:beef","weight":6,"type":"item"},{"functions":[{"function":"set_count","count":{"max":3,"min":1}}],"name":"minecraft:muttonRaw","weight":6,"type":"item"},{"functions":[{"function":"set_count","count":{"max":3,"min":1}}],"name":"minecraft:coal","weight":3,"type":"item"}],"rolls":{"max":5,"min":1}}]}